thonny/VERSION
thonny/__init__.py
thonny/__main__.py
thonny/assistance.py
thonny/ast_utils.py
thonny/backend.py
thonny/base_file_browser.py
thonny/codeview.py
thonny/common.py
thonny/config.py
thonny/config_ui.py
thonny/defaults.ini
thonny/editor_helpers.py
thonny/editors.py
thonny/export.py
thonny/first_run.py
thonny/gridtable.py
thonny/jedi_utils.py
thonny/languages.py
thonny/memory.py
thonny/misc_utils.py
thonny/roughparse.py
thonny/rst_utils.py
thonny/running.py
thonny/shell.py
thonny/terminal.py
thonny/tktextext.py
thonny/token_utils.py
thonny/udisks.py
thonny/ui_utils.py
thonny/workbench.py
thonny/workdlg.py
thonny/dbus/org.freedesktop.DBus.ObjectManager.xml
thonny/dbus/org.freedesktop.UDisks2.xml
thonny/locale/.DS_Store
thonny/locale/compile_mo.bat
thonny/locale/register_updates.py
thonny/locale/thonny.pot
thonny/locale/update_pot.bat
thonny/locale/ar_AR/LC_MESSAGES/thonny.mo
thonny/locale/ar_AR/LC_MESSAGES/thonny.po
thonny/locale/be_BY/LC_MESSAGES/thonny.mo
thonny/locale/be_BY/LC_MESSAGES/thonny.po
thonny/locale/ca_ES/LC_MESSAGES/thonny.mo
thonny/locale/ca_ES/LC_MESSAGES/thonny.po
thonny/locale/cs_CZ/LC_MESSAGES/thonny.mo
thonny/locale/cs_CZ/LC_MESSAGES/thonny.po
thonny/locale/de_DE/LC_MESSAGES/thonny.mo
thonny/locale/de_DE/LC_MESSAGES/thonny.po
thonny/locale/el_GR/LC_MESSAGES/thonny.mo
thonny/locale/el_GR/LC_MESSAGES/thonny.po
thonny/locale/en_GB/LC_MESSAGES/thonny.mo
thonny/locale/en_GB/LC_MESSAGES/thonny.po
thonny/locale/en_US/LC_MESSAGES/thonny.mo
thonny/locale/en_US/LC_MESSAGES/thonny.po
thonny/locale/es_ES/HELP_CONTENT/debuggers.rst
thonny/locale/es_ES/HELP_CONTENT/debugging.rst
thonny/locale/es_ES/HELP_CONTENT/errors.rst
thonny/locale/es_ES/LC_MESSAGES/thonny.mo
thonny/locale/es_ES/LC_MESSAGES/thonny.po
thonny/locale/et_EE/LC_MESSAGES/thonny.mo
thonny/locale/et_EE/LC_MESSAGES/thonny.po
thonny/locale/eu_ES/LC_MESSAGES/thonny.mo
thonny/locale/eu_ES/LC_MESSAGES/thonny.po
thonny/locale/fa_IR/LC_MESSAGES/thonny.mo
thonny/locale/fa_IR/LC_MESSAGES/thonny.po
thonny-4.1.6.dist-info/LICENSE.txt
thonny-4.1.6.dist-info/METADATA
thonny-4.1.6.dist-info/WHEEL
thonny-4.1.6.dist-info/entry_points.txt
thonny-4.1.6.dist-info/top_level.txt
thonny-4.1.6.dist-info/RECORD
